apiai/VAD.py
apiai/__init__.py
apiai/apiai.py
apiai/resampler.py
apiai/requests/__init__.py
apiai/requests/request.py
apiai/requests/query/__init__.py
apiai/requests/query/events.py
apiai/requests/query/query.py
apiai/requests/query/text.py
apiai/requests/query/voice.py
apiai/requests/user_entities/__init__.py
apiai/requests/user_entities/user_entities_request.py
apiai-1.2.3.dist-info/DESCRIPTION.rst
apiai-1.2.3.dist-info/METADATA
apiai-1.2.3.dist-info/RECORD
apiai-1.2.3.dist-info/WHEEL
apiai-1.2.3.dist-info/metadata.json
apiai-1.2.3.dist-info/top_level.txt
