Metadata-Version: 1.0
Name: apiai
Version: 1.2.3
Summary: The API.AI iOS SDK makes it easy to integrate speech recognition with API.AI natural language processing API on iOS devices.
Home-page: https://api.ai/
Author: Dmitriy Kuragin
Author-email: kuragin@speaktoit.com
License: Apache 2.0
Platform: UNKNOWN
